lapidary/render/__init__.py
lapidary/render/__main__.py
lapidary/render/cli.py
lapidary/render/config.py
lapidary/render/json_pointer.py
lapidary/render/load.py
lapidary/render/main.py
lapidary/render/model/__init__.py
lapidary/render/model/conv_cst.py
lapidary/render/model/conv_openapi.py
lapidary/render/model/conv_schema.py
lapidary/render/model/metamodel.py
lapidary/render/model/openapi/__init__.py
lapidary/render/model/openapi/base.py
lapidary/render/model/openapi/model.py
lapidary/render/model/python/__init__.py
lapidary/render/model/python/model.py
lapidary/render/model/python/module.py
lapidary/render/model/python/module_path.py
lapidary/render/model/python/type_hint.py
lapidary/render/model/refs.py
lapidary/render/model/stack.py
lapidary/render/names.py
lapidary/render/pydantic_utils.py
lapidary/render/pyproject.py
lapidary/render/runtime.py
lapidary/render/writer.py
lapidary/render/yaml.py
lapidary_render-0.12.1.dist-info/METADATA
lapidary_render-0.12.1.dist-info/WHEEL
lapidary_render-0.12.1.dist-info/entry_points.txt
lapidary_render-0.12.1.dist-info/RECORD
